ovcfg/__init__.py
ovcfg/__main__.py
ovcfg/ovcfg.py
ovcfg-1.3.2.dist-info/LICENSE.txt
ovcfg-1.3.2.dist-info/METADATA
ovcfg-1.3.2.dist-info/WHEEL
ovcfg-1.3.2.dist-info/top_level.txt
ovcfg-1.3.2.dist-info/RECORD
