Metadata-Version: 2.1
Name: ovcfg
Version: 1.3.2
Summary: OvCfg
Home-page: 
Author: Dmitry Yakovlev
Author-email: opensuse12@gmail.com
Requires-Python: >=3.5
License-File: LICENSE.txt
